pysachi/__init__.py
pysachi/__main__.py
pysachi/__pkginfo__.py
pysachi/analyzer.py
pysachi/renderer.py
pysachi/report.py
pysachi/sachi.py
pysachi/xml.py
pysachi/rules/__init__.py
pysachi/rules/function.py
pysachi-0.1.1.dist-info/LICENSE
pysachi-0.1.1.dist-info/METADATA
pysachi-0.1.1.dist-info/WHEEL
pysachi-0.1.1.dist-info/top_level.txt
pysachi-0.1.1.dist-info/RECORD
