Metadata-Version: 2.1
Name: pysachi
Version: 0.1.1
Summary: UNKNOWN
Home-page: UNKNOWN
License: UNKNOWN
Platform: UNKNOWN
Requires-Python: >=3.4.*
